tokenize_output/__init__.py
tokenize_output/tokenize_output.py
tokenize_output-0.4.10.data/scripts/tokenize-output
tokenize_output-0.4.10.dist-info/LICENSE
tokenize_output-0.4.10.dist-info/METADATA
tokenize_output-0.4.10.dist-info/WHEEL
tokenize_output-0.4.10.dist-info/top_level.txt
tokenize_output-0.4.10.dist-info/RECORD
