Metadata-Version: 2.1
Name: tokenize-output
Version: 0.4.10
Summary: Get identifiers, names, paths, URLs and words from the command output.
Home-page: https://github.com/anki-code/tokenize-output
Author: anki-code
Author-email: author@example.com
License: BSD
Project-URL: Documentation, https://github.com/anki-code/tokenize-output/blob/master/README.md
Project-URL: Code, https://github.com/anki-code/tokenize-output
Project-URL: Issue tracker, https://github.com/anki-code/tokenize-output/issues
Platform: any
Classifier: Programming Language :: Python
Requires-Python: >=3.6
License-File: LICENSE
Requires-Dist: demjson3
Provides-Extra: dev
Requires-Dist: pytest ; extra == 'dev'
